cherry_core-0.6.1.dist-info/METADATA
cherry_core-0.6.1.dist-info/WHEEL
cherry_core-0.6.1.dist-info/licenses/LICENSE-APACHE
cherry_core-0.6.1.dist-info/licenses/LICENSE-MIT
cherry_core/__init__.py
cherry_core/cherry_core.cpython-312-darwin.so
cherry_core/ingest/__init__.py
cherry_core/ingest/evm.py
cherry_core/ingest/svm.py
cherry_core/svm_decode/__init__.py
cherry_core-0.6.1.dist-info/RECORD
