Metadata-Version: 2.4
Name: cherry-core
Version: 0.6.1
Classifier: Programming Language :: Rust
Classifier: Programming Language :: Python :: Implementation :: CPython
Classifier: Programming Language :: Python :: Implementation :: PyPy
License-File: LICENSE-APACHE
License-File: LICENSE-MIT
Summary: Core library for cherry blockchain data framework
Home-Page: https://github.com/steelcake/cherry-core
Author: Ozgur Akkurt <oezgurmakkurt@gmail.com>
Author-email: Ozgur Akkurt <oezgurmakkurt@gmail.com>
License: MIT OR Apache-2.0
Requires-Python: >=3.8
Project-URL: Source Code, https://github.com/steelcake/cherry-core
